rds_provider/manifest.toml
rds_provider/rds_provider.py
rds_provider/test_rds_provider.py
opsbox_rds_provider-0.1.5.dist-info/LICENCE.txt
opsbox_rds_provider-0.1.5.dist-info/METADATA
opsbox_rds_provider-0.1.5.dist-info/WHEEL
opsbox_rds_provider-0.1.5.dist-info/entry_points.txt
opsbox_rds_provider-0.1.5.dist-info/top_level.txt
opsbox_rds_provider-0.1.5.dist-info/RECORD
